MANIFEST.in
requirements.txt
setup.py
pystol/__init__.py
pystol/cleaner.py
pystol/cli.py
pystol/const.py
pystol/deployer.py
pystol/get_banner.py
pystol/lister.py
pystol/logger.py
pystol/operator.py
pystol.egg-info/PKG-INFO
pystol.egg-info/SOURCES.txt
pystol.egg-info/dependency_links.txt
pystol.egg-info/entry_points.txt
pystol.egg-info/requires.txt
pystol.egg-info/top_level.txt
pystol/templates/latest/pystol.clusterrole.yaml
pystol/templates/latest/pystol.clusterrolebinding.yaml
pystol/templates/latest/pystol.configmap.yaml.j2
pystol/templates/latest/pystol.controller.yaml.j2
pystol/templates/latest/pystol.crd.yaml
pystol/templates/latest/pystol.kuberegistry.yaml
pystol/templates/latest/pystol.localhostvalues.yaml
pystol/templates/latest/pystol.namespace.yaml
pystol/templates/latest/pystol.service.yaml
pystol/templates/latest/pystol.serviceaccount.yaml
pystol/templates/latest/pystol.ui.yaml.j2
pystol/templates/latest/pystol.upstreamvalues.yaml
pystol/templates/operatorhub/pystol/pystol.package.yaml
pystol/templates/operatorhub/pystol/0.8.17/pystol.clusterrolebinding.yaml
pystol/templates/operatorhub/pystol/0.8.17/pystol.crd.yaml
pystol/templates/operatorhub/pystol/0.8.17/pystol.service.yaml
pystol/templates/operatorhub/pystol/0.8.17/pystol.v0.8.17.clusterserviceversion.yaml